belink_plugin/.DS_Store
belink_plugin/__init__.py
belink_plugin/config/__init__.py
belink_plugin/config/__pycache__/config.cpython-312.pyc
belink_plugin/config/__pycache__/logger_format.cpython-312.pyc
belink_plugin/config/config.py
belink_plugin/config/logger_format.py
belink_plugin/core/__init__.py
belink_plugin/core/__pycache__/__init__.cpython-312.pyc
belink_plugin/core/__pycache__/plugin_executor.cpython-312.pyc
belink_plugin/core/__pycache__/plugin_registration.cpython-312.pyc
belink_plugin/core/entities/__init__.py
belink_plugin/core/entities/__pycache__/__init__.cpython-312.pyc
belink_plugin/core/entities/plugin/__pycache__/request.cpython-312.pyc
belink_plugin/core/entities/plugin/__pycache__/setup.cpython-312.pyc
belink_plugin/core/entities/plugin/request.py
belink_plugin/core/entities/plugin/setup.py
belink_plugin/core/plugin_executor.py
belink_plugin/core/plugin_registration.py
belink_plugin/core/server/__pycache__/http_server.cpython-312.pyc
belink_plugin/core/server/http_server.py
belink_plugin/core/utils/__init__.py
belink_plugin/core/utils/__pycache__/__init__.cpython-312.pyc
belink_plugin/core/utils/__pycache__/class_loader.cpython-312.pyc
belink_plugin/core/utils/__pycache__/yaml_loader.cpython-312.pyc
belink_plugin/core/utils/class_loader.py
belink_plugin/core/utils/yaml_loader.py
belink_plugin/entities/__init__.py
belink_plugin/entities/__pycache__/__init__.cpython-312.pyc
belink_plugin/entities/__pycache__/agent.cpython-312.pyc
belink_plugin/entities/__pycache__/tool.cpython-312.pyc
belink_plugin/entities/agent.py
belink_plugin/entities/model/__init__.py
belink_plugin/entities/model/__pycache__/__init__.cpython-312.pyc
belink_plugin/entities/model/__pycache__/message.cpython-312.pyc
belink_plugin/entities/model/message.py
belink_plugin/entities/tool.py
belink_plugin/errors/__init__.py
belink_plugin/errors/__pycache__/__init__.cpython-312.pyc
belink_plugin/errors/__pycache__/tool.cpython-312.pyc
belink_plugin/errors/tool.py
belink_plugin-0.0.1.dist-info/LICENSE
belink_plugin-0.0.1.dist-info/METADATA
belink_plugin-0.0.1.dist-info/WHEEL
belink_plugin-0.0.1.dist-info/RECORD
